pymhlib/__init__.py
pymhlib/aggregate_results.py
pymhlib/alns.py
pymhlib/binvec_solution.py
pymhlib/decision_diag.py
pymhlib/gvns.py
pymhlib/log.py
pymhlib/multi_run_summary.py
pymhlib/par_alns.py
pymhlib/pbig.py
pymhlib/permutation_solution.py
pymhlib/population.py
pymhlib/sa.py
pymhlib/scheduler.py
pymhlib/settings.py
pymhlib/solution.py
pymhlib/ssga.py
pymhlib/subsetvec_solution.py
pymhlib/demos/__init__.py
pymhlib/demos/common.py
pymhlib/demos/dd_mkp.py
pymhlib/demos/graph_coloring.py
pymhlib/demos/graphs.py
pymhlib/demos/julia-maxsat.py
pymhlib/demos/julia-maxsat2.py
pymhlib/demos/maxsat.py
pymhlib/demos/misp.py
pymhlib/demos/mkp.py
pymhlib/demos/qap.py
pymhlib/demos/tsp.py
pymhlib/demos/vertex_cover.py
pymhlib/demos/data/bur26a.dat
pymhlib/demos/data/fpsol2.i.1.col
pymhlib/demos/data/frb40-19-1.mis
pymhlib/demos/data/maxsat-adv1.cnf
pymhlib/demos/data/maxsat-adv2.cnf
pymhlib/demos/data/maxsat-simple.cnf
pymhlib/demos/data/mknap-small.txt
pymhlib/demos/data/mknapcb5-01.txt
pymhlib/demos/data/xqf131.tsp
pymhlib/tests/__init__.py
pymhlib/tests/test_all.py
pymhlib-0.1.5.dist-info/LICENSE
pymhlib-0.1.5.dist-info/METADATA
pymhlib-0.1.5.dist-info/WHEEL
pymhlib-0.1.5.dist-info/top_level.txt
pymhlib-0.1.5.dist-info/RECORD
