Metadata-Version: 2.1
Name: pymhlib
Version: 0.1.5
Summary: pymhlib - a toolbox for metaheuristics and hybrid optimization methods
Home-page: https://github.com/ac-tuwien/pymhlib
Author: Günther Raidl et al.
Author-email: raidl@ac.tuwien.ac.at
License: GPL3
Platform: UNKNOWN
Classifier: Programming Language :: Python :: 3
Classifier: License :: OSI Approved :: GNU General Public License v3 (GPLv3)
Classifier: Operating System :: OS Independent
Requires-Python: >=3.7
